{
    "class android::hardware::camera2::params::OutputConfiguration": {
        "variable": [
            {
                "count": 1,
                "self_constraint": [],
                "name": "mRotation",
                "under_constraint": [],
                "dependency": [],
                "relation": [],
                "signature": "int",
                "serialization_type": 2,
                "usedBy": [],
                "type": "int",
                "loop": []
            },
            {
                "count": 1,
                "self_constraint": [
                    "constraint1",
                    "constraint2",
                    "constraint3",
                    "constraint4",
                    "constraint5",
                    "constraint7",
                    "constraint9",
                    "constraint10",
                    "constraint11"
                ],
                "name": "err",
                "under_constraint": [],
                "dependency": [],
                "relation": [],
                "serialization_type": 0,
                "usedBy": [],
                "type": "android::status_t",
                "loop": []
            },
            {
                "count": 1,
                "self_constraint": [],
                "name": "mSurfaceSetID",
                "under_constraint": [],
                "dependency": [],
                "relation": [],
                "signature": "int",
                "serialization_type": 2,
                "usedBy": [],
                "type": "int",
                "loop": []
            },
            {
                "count": 1,
                "self_constraint": [],
                "name": "mSurfaceType",
                "under_constraint": [],
                "dependency": [],
                "relation": [],
                "signature": "int",
                "serialization_type": 2,
                "usedBy": [],
                "type": "int",
                "loop": []
            },
            {
                "count": 1,
                "self_constraint": [],
                "name": "mWidth",
                "under_constraint": [],
                "dependency": [],
                "relation": [],
                "signature": "int",
                "serialization_type": 2,
                "usedBy": [],
                "type": "int",
                "loop": []
            },
            {
                "count": 1,
                "self_constraint": [],
                "name": "mHeight",
                "under_constraint": [],
                "dependency": [],
                "relation": [],
                "signature": "int",
                "serialization_type": 2,
                "usedBy": [],
                "type": "int",
                "loop": []
            },
            {
                "count": 1,
                "self_constraint": [],
                "name": "implicit_7",
                "under_constraint": [
                    {
                        "status": true,
                        "name": "constraint6"
                    }
                ],
                "value": 1,
                "dependency": [],
                "relation": [],
                "serialization_type": 2,
                "usedBy": [],
                "type": "IntegerLiteral",
                "loop": []
            },
            {
                "count": 1,
                "self_constraint": [],
                "name": "implicit_8",
                "under_constraint": [
                    {
                        "status": false,
                        "name": "constraint6"
                    }
                ],
                "value": 0,
                "dependency": [],
                "relation": [],
                "serialization_type": 2,
                "usedBy": [],
                "type": "IntegerLiteral",
                "loop": []
            },
            {
                "count": 1,
                "self_constraint": [],
                "name": "implicit_10",
                "under_constraint": [
                    {
                        "status": true,
                        "name": "constraint8"
                    }
                ],
                "value": 1,
                "dependency": [],
                "relation": [],
                "serialization_type": 2,
                "usedBy": [],
                "type": "IntegerLiteral",
                "loop": []
            },
            {
                "count": 1,
                "self_constraint": [],
                "name": "implicit_11",
                "under_constraint": [
                    {
                        "status": false,
                        "name": "constraint8"
                    }
                ],
                "value": 0,
                "dependency": [],
                "relation": [],
                "serialization_type": 2,
                "usedBy": [],
                "type": "IntegerLiteral",
                "loop": []
            },
            {
                "count": 1,
                "self_constraint": [],
                "name": "surfaceShims",
                "dependency": [],
                "under_constraint": [],
                "have_parcelable": 1,
                "relation": [],
                "serialization_type": 2,
                "usedBy": [],
                "type": "class vector<class android::view::Surface>",
                "loop": [],
                "size": -1
            },
            {
                "count": 1,
                "self_constraint": [],
                "name": "surfaceShims::item",
                "dependency": [],
                "under_constraint": [],
                "have_parcelable": 1,
                "relation": [],
                "serialization_type": 2,
                "usedBy": [],
                "type": "class android::view::Surface",
                "loop": []
            },
            {
                "count": 1,
                "self_constraint": [],
                "name": "mPhysicalCameraId",
                "under_constraint": [],
                "dependency": [],
                "relation": [],
                "signature": "class android::String16",
                "serialization_type": 2,
                "usedBy": [],
                "type": "class android::String16",
                "loop": []
            },
            {
                "count": 1,
                "self_constraint": [],
                "name": "android::OK",
                "under_constraint": [],
                "value": 0,
                "dependency": [],
                "relation": [],
                "serialization_type": 0,
                "usedBy": [],
                "type": "android::status_t",
                "loop": []
            }
        ],
        "dependency": [],
        "loop": [],
        "possibility": [
            {
                "return": "android::OK",
                "reply": [
                    "mRotation",
                    "mSurfaceSetID",
                    "mSurfaceType",
                    "mWidth",
                    "mHeight",
                    "implicit_7",
                    "implicit_8",
                    "implicit_10",
                    "implicit_11",
                    "surfaceShims",
                    "mPhysicalCameraId"
                ],
                "data": [],
                "id": 0
            }
        ],
        "constraint": [
            {
                "lhs": {
                    "type": "class android::Parcel *",
                    "name": "parcel"
                },
                "rhs": {
                    "type": "class android::Parcel *",
                    "name": "implicit_1",
                    "value": "NULL"
                },
                "opcode": "==",
                "name": "constraint0",
                "probability": 0.5
            },
            {
                "lhs": {
                    "type": "android::status_t",
                    "name": "err"
                },
                "rhs": {
                    "type": "android::status_t",
                    "name": "android::OK",
                    "value": 0
                },
                "opcode": "!=",
                "name": "constraint1",
                "probability": 0.5
            },
            {
                "lhs": {
                    "type": "android::status_t",
                    "name": "err"
                },
                "rhs": {
                    "type": "android::status_t",
                    "name": "android::OK",
                    "value": 0
                },
                "opcode": "!=",
                "name": "constraint2",
                "probability": 0.5
            },
            {
                "lhs": {
                    "type": "android::status_t",
                    "name": "err"
                },
                "rhs": {
                    "type": "android::status_t",
                    "name": "android::OK",
                    "value": 0
                },
                "opcode": "!=",
                "name": "constraint3",
                "probability": 0.5
            },
            {
                "lhs": {
                    "type": "android::status_t",
                    "name": "err"
                },
                "rhs": {
                    "type": "android::status_t",
                    "name": "android::OK",
                    "value": 0
                },
                "opcode": "!=",
                "name": "constraint4",
                "probability": 0.5
            },
            {
                "lhs": {
                    "type": "android::status_t",
                    "name": "err"
                },
                "rhs": {
                    "type": "android::status_t",
                    "name": "android::OK",
                    "value": 0
                },
                "opcode": "!=",
                "name": "constraint5",
                "probability": 0.5
            },
            {
                "lhs": {
                    "type": "_Bool",
                    "name": "mIsDeferred",
                    "signature": "_Bool"
                },
                "opcode": "",
                "name": "constraint6",
                "probability": 0.5
            },
            {
                "lhs": {
                    "type": "android::status_t",
                    "name": "err"
                },
                "rhs": {
                    "type": "android::status_t",
                    "name": "android::OK",
                    "value": 0
                },
                "opcode": "!=",
                "name": "constraint7",
                "probability": 0.5
            },
            {
                "lhs": {
                    "type": "_Bool",
                    "name": "mIsShared",
                    "signature": "_Bool"
                },
                "opcode": "",
                "name": "constraint8",
                "probability": 0.5
            },
            {
                "lhs": {
                    "type": "android::status_t",
                    "name": "err"
                },
                "rhs": {
                    "type": "android::status_t",
                    "name": "android::OK",
                    "value": 0
                },
                "opcode": "!=",
                "name": "constraint9",
                "probability": 0.5
            },
            {
                "lhs": {
                    "type": "android::status_t",
                    "name": "err"
                },
                "rhs": {
                    "type": "android::status_t",
                    "name": "android::OK",
                    "value": 0
                },
                "opcode": "!=",
                "name": "constraint10",
                "probability": 0.5
            },
            {
                "lhs": {
                    "type": "android::status_t",
                    "name": "err"
                },
                "rhs": {
                    "type": "android::status_t",
                    "name": "android::OK",
                    "value": 0
                },
                "opcode": "!=",
                "name": "constraint11",
                "probability": 0.5
            }
        ]
    }
}