{
    "class android::os::DropBoxManager::Entry": {
        "variable": [
            {
                "count": 1,
                "self_constraint": [],
                "name": "mTag",
                "under_constraint": [],
                "dependency": [],
                "relation": [],
                "signature": "class android::String16",
                "serialization_type": 2,
                "usedBy": [],
                "type": "class android::String16",
                "loop": []
            },
            {
                "count": 1,
                "self_constraint": [
                    "constraint0",
                    "constraint1",
                    "constraint3",
                    "constraint4",
                    "constraint5",
                    "constraint6"
                ],
                "name": "err",
                "under_constraint": [],
                "dependency": [],
                "relation": [],
                "serialization_type": 0,
                "usedBy": [],
                "type": "android::status_t",
                "loop": []
            },
            {
                "count": 1,
                "self_constraint": [],
                "name": "mTimeMillis",
                "under_constraint": [
                    {
                        "status": false,
                        "name": "constraint0"
                    }
                ],
                "dependency": [],
                "relation": [],
                "signature": "int64_t",
                "serialization_type": 2,
                "usedBy": [],
                "type": "long long",
                "loop": []
            },
            {
                "count": 1,
                "self_constraint": [
                    "constraint2"
                ],
                "name": "android::os::DropBoxManager::Entry::mFd",
                "under_constraint": [
                    {
                        "status": false,
                        "name": "constraint0"
                    },
                    {
                        "status": false,
                        "name": "constraint1"
                    },
                    {
                        "status": true,
                        "name": "constraint2"
                    },
                    {
                        "status": false,
                        "name": "constraint3"
                    }
                ],
                "dependency": [],
                "relation": [],
                "serialization_type": 2,
                "usedBy": [],
                "type": "FileDescriptor",
                "loop": []
            },
            {
                "count": 1,
                "self_constraint": [],
                "name": "implicit_4",
                "under_constraint": [
                    {
                        "status": false,
                        "name": "constraint0"
                    },
                    {
                        "status": false,
                        "name": "constraint1"
                    },
                    {
                        "status": true,
                        "name": "constraint2"
                    }
                ],
                "dependency": [],
                "relation": [],
                "serialization_type": 2,
                "usedBy": [],
                "type": "int",
                "loop": []
            },
            {
                "count": 1,
                "self_constraint": [],
                "name": "implicit_7",
                "under_constraint": [
                    {
                        "status": false,
                        "name": "constraint0"
                    },
                    {
                        "status": false,
                        "name": "constraint1"
                    },
                    {
                        "status": false,
                        "name": "constraint2"
                    },
                    {
                        "status": false,
                        "name": "constraint3"
                    },
                    {
                        "status": false,
                        "name": "constraint4"
                    }
                ],
                "dependency": [],
                "relation": [],
                "serialization_type": 2,
                "usedBy": [],
                "type": "int",
                "loop": []
            },
            {
                "count": 1,
                "self_constraint": [],
                "name": "mData",
                "under_constraint": [
                    {
                        "status": false,
                        "name": "constraint0"
                    },
                    {
                        "status": false,
                        "name": "constraint1"
                    },
                    {
                        "status": false,
                        "name": "constraint2"
                    },
                    {
                        "status": false,
                        "name": "constraint3"
                    },
                    {
                        "status": false,
                        "name": "constraint4"
                    },
                    {
                        "status": false,
                        "name": "constraint5"
                    }
                ],
                "dependency": [],
                "relation": [],
                "signature": "vector<uint8_t>",
                "serialization_type": 2,
                "usedBy": [],
                "type": "class vector<unsigned char>",
                "loop": [],
                "size": -1
            },
            {
                "count": 1,
                "self_constraint": [],
                "name": "mData::item",
                "under_constraint": [],
                "dependency": [],
                "relation": [],
                "signature": "vector<uint8_t>",
                "serialization_type": 2,
                "usedBy": [],
                "type": "unsigned char",
                "loop": []
            },
            {
                "count": 1,
                "self_constraint": [],
                "name": "android::NO_ERROR",
                "under_constraint": [
                    {
                        "status": false,
                        "name": "constraint0"
                    },
                    {
                        "status": false,
                        "name": "constraint1"
                    },
                    {
                        "status": false,
                        "name": "constraint2"
                    },
                    {
                        "status": false,
                        "name": "constraint3"
                    },
                    {
                        "status": false,
                        "name": "constraint4"
                    },
                    {
                        "status": false,
                        "name": "constraint5"
                    }
                ],
                "value": 0,
                "dependency": [],
                "relation": [],
                "serialization_type": 0,
                "usedBy": [],
                "type": "android::status_t",
                "loop": []
            }
        ],
        "dependency": [
            {
                "filename": "BnDropBoxManagerService.json",
                "type": "Transaction",
                "name": "IDropBoxManagerService::3-3",
                "possIdx": 0,
                "varIdx": 1,
                "varName": "_aidl_return",
                "varType": "class android::os::DropBoxManager::Entry"
            }
        ],
        "loop": [],
        "possibility": [
            {
                "return": "err",
                "reply": [
                    "mTag"
                ],
                "data": [],
                "id": 0
            },
            {
                "return": "err",
                "reply": [
                    "mTag",
                    "mTimeMillis"
                ],
                "data": [],
                "id": 1
            },
            {
                "return": "err",
                "reply": [
                    "mTag",
                    "mTimeMillis",
                    "implicit_4"
                ],
                "data": [],
                "id": 2
            },
            {
                "return": "err",
                "reply": [
                    "mTag",
                    "mTimeMillis",
                    "implicit_4",
                    "android::os::DropBoxManager::Entry::mFd"
                ],
                "data": [],
                "id": 3
            },
            {
                "return": "err",
                "reply": [
                    "mTag",
                    "mTimeMillis",
                    "implicit_4",
                    "android::os::DropBoxManager::Entry::mFd",
                    "implicit_7"
                ],
                "data": [],
                "id": 4
            },
            {
                "return": "err",
                "reply": [
                    "mTag",
                    "mTimeMillis",
                    "implicit_4",
                    "android::os::DropBoxManager::Entry::mFd",
                    "implicit_7",
                    "mData"
                ],
                "data": [],
                "id": 5
            },
            {
                "return": "android::NO_ERROR",
                "reply": [
                    "mTag",
                    "mTimeMillis",
                    "implicit_4",
                    "android::os::DropBoxManager::Entry::mFd",
                    "implicit_7",
                    "mData"
                ],
                "data": [],
                "id": 6
            }
        ],
        "constraint": [
            {
                "lhs": {
                    "type": "android::status_t",
                    "name": "err"
                },
                "rhs": {
                    "type": "android::status_t",
                    "name": "android::NO_ERROR",
                    "value": 0
                },
                "opcode": "!=",
                "name": "constraint0",
                "probability": 0.1
            },
            {
                "lhs": {
                    "type": "android::status_t",
                    "name": "err"
                },
                "rhs": {
                    "type": "android::status_t",
                    "name": "android::NO_ERROR",
                    "value": 0
                },
                "opcode": "!=",
                "name": "constraint1",
                "probability": 0.1
            },
            {
                "lhs": {
                    "serialization_type": 0,
                    "type": "FileDescriptor",
                    "name": "android::os::DropBoxManager::Entry::mFd"
                },
                "rhs": {
                    "lhs": {
                        "type": "IntegerLiteral",
                        "name": "implicit_3",
                        "value": -1
                    },
                    "opcode": "-"
                },
                "opcode": "!=",
                "name": "constraint2",
                "probability": 0.5
            },
            {
                "lhs": {
                    "type": "android::status_t",
                    "name": "err"
                },
                "rhs": {
                    "type": "android::status_t",
                    "name": "android::NO_ERROR",
                    "value": 0
                },
                "opcode": "!=",
                "name": "constraint3",
                "probability": 0.1
            },
            {
                "lhs": {
                    "type": "android::status_t",
                    "name": "err"
                },
                "rhs": {
                    "type": "android::status_t",
                    "name": "android::NO_ERROR",
                    "value": 0
                },
                "opcode": "!=",
                "name": "constraint4",
                "probability": 0.1
            },
            {
                "lhs": {
                    "type": "android::status_t",
                    "name": "err"
                },
                "rhs": {
                    "type": "android::status_t",
                    "name": "android::NO_ERROR",
                    "value": 0
                },
                "opcode": "!=",
                "name": "constraint5",
                "probability": 0.1
            },
            {
                "lhs": {
                    "type": "android::status_t",
                    "name": "err"
                },
                "rhs": {
                    "type": "android::status_t",
                    "name": "android::NO_ERROR",
                    "value": 0
                },
                "opcode": "!=",
                "name": "constraint6",
                "probability": 0.1
            }
        ]
    }
}